hdu/__init__.py
hdu/_version.py
hdu/hdu.py
hdu-0.2.3.12.dist-info/DESCRIPTION.rst
hdu-0.2.3.12.dist-info/METADATA
hdu-0.2.3.12.dist-info/RECORD
hdu-0.2.3.12.dist-info/WHEEL
hdu-0.2.3.12.dist-info/entry_points.txt
hdu-0.2.3.12.dist-info/metadata.json
hdu-0.2.3.12.dist-info/top_level.txt
