Metadata-Version: 2.0
Name: hdu
Version: 0.2.3.12
Summary: Human-friendly summary of disk usage.
Home-page: https://github.com/norok2/hdu
Author: Riccardo Metere
Author-email: rick@metere.it
License: GPLv3+
Keywords: hdu,du,disk,usage,console,cli,tui
Platform: UNKNOWN
Classifier: Development Status :: 4 - Beta
Classifier: Intended Audience :: System Administrators
Classifier: Topic :: System :: Shells
Classifier: Topic :: System :: Systems Administration
Classifier: Topic :: System :: Filesystems
Classifier: Topic :: System :: Monitoring
Classifier: Topic :: Utilities
Classifier: Operating System :: POSIX
Classifier: License :: OSI Approved :: GNU General Public License v3 or later (GPLv3+)
Classifier: Programming Language :: Python
Classifier: Programming Language :: Python :: 2
Classifier: Programming Language :: Python :: 3
Provides-Extra: blessed
Provides-Extra: blessed
Requires-Dist: blessed; extra == 'blessed'
